taxengine/__init__.py
taxengine/shared/__init__.py
taxengine/shared/model/__init__.py
taxengine/shared/model/base.py
taxengine/shared/model/models.py
calyx_taxengine-0.0.5.dist-info/LICENCE
calyx_taxengine-0.0.5.dist-info/METADATA
calyx_taxengine-0.0.5.dist-info/WHEEL
calyx_taxengine-0.0.5.dist-info/top_level.txt
calyx_taxengine-0.0.5.dist-info/RECORD
