Metadata-Version: 2.1
Name: calyx-taxengine
Version: 0.0.5
Summary: Tax Engine shered module
Home-page: UNKNOWN
Author: Calyx Servicios
Author-email: <dev@calyxservicios.com.ar>
License: UNKNOWN
Keywords: calyx-servicios,tax-engine
Platform: UNKNOWN
Requires-Dist: sqlalchemy
